tools_lzy/__init__.py
tools_lzy/audio/__init__.py
tools_lzy/image/__init__.py
tools_lzy/io/__init__.py
tools_lzy/utils/__init__.py
tools_lzy/utils/uuid.py
tools_lzy/video/__init__.py
tools_lzy-0.0.2.dist-info/LICENSE.txt
tools_lzy-0.0.2.dist-info/METADATA
tools_lzy-0.0.2.dist-info/WHEEL
tools_lzy-0.0.2.dist-info/top_level.txt
tools_lzy-0.0.2.dist-info/RECORD
