Metadata-Version: 2.1
Name: tools-lzy
Version: 0.0.2
Summary: Some tools
Home-page: UNKNOWN
Author: lucky_lzy
Author-email: lucky_lzy@126.com
License: UNKNOWN
Platform: UNKNOWN
Classifier: Programming Language :: Python :: 3
Classifier: License :: OSI Approved :: MIT License
Classifier: Operating System :: OS Independent
Requires-Python: >=3.6
License-File: LICENSE.txt
